README.md
setup.py
outputformat/__init__.py
outputformat/color.py
outputformat/dict.py
outputformat/emoji.py
outputformat/fonts.py
outputformat/list.py
outputformat/misc.py
outputformat/plot.py
outputformat/title.py
outputformat/tools.py
outputformat.egg-info/PKG-INFO
outputformat.egg-info/SOURCES.txt
outputformat.egg-info/dependency_links.txt
outputformat.egg-info/top_level.txt